recipebox_pkg/__init__.py
recipebox_pkg/fetch_recipe.py
recipebox_pkg/id_search.py
recipebox_pkg/ing_search.py
recipebox_pkg/nutr_search.py
recipebox_pkg-2.2.2.dist-info/LICENSE
recipebox_pkg-2.2.2.dist-info/METADATA
recipebox_pkg-2.2.2.dist-info/WHEEL
recipebox_pkg-2.2.2.dist-info/RECORD
