Metadata-Version: 2.1
Name: recipebox_pkg
Version: 2.2.2
Summary: A Python package designed for fetching information about recipes.
License: MIT
Author: Yuchen An
Requires-Python: >=3.9,<4.0
Classifier: License :: OSI Approved :: MIT License
Classifier: Programming Language :: Python :: 3
Classifier: Programming Language :: Python :: 3.9
Classifier: Programming Language :: Python :: 3.10
Classifier: Programming Language :: Python :: 3.11
Requires-Dist: pandas (>=1.4.2,<2.0.0)
Requires-Dist: requests (>=2.31.0,<3.0.0)
